fastapi_simple_rate_limiter/__init__.py
fastapi_simple_rate_limiter/database.py
fastapi_simple_rate_limiter/exception.py
fastapi_simple_rate_limiter/limiter.py
fastapi_simple_rate_limiter-0.0.7.dist-info/LICENSE
fastapi_simple_rate_limiter-0.0.7.dist-info/METADATA
fastapi_simple_rate_limiter-0.0.7.dist-info/WHEEL
fastapi_simple_rate_limiter-0.0.7.dist-info/RECORD
