Metadata-Version: 2.1
Name: fastapi-simple-rate-limiter
Version: 0.0.7
Summary: Rate limiter to limit the number of API requests in FastAPI
Author: jintaekimmm
Author-email: jintae.kimmm@gmail.com
Requires-Python: >=3.10,<4.0
Classifier: Programming Language :: Python :: 3
Classifier: Programming Language :: Python :: 3.10
Classifier: Programming Language :: Python :: 3.11
Requires-Dist: redis (>=5.0.1,<6.0.0)
